nf9/__init__.py
nf9/nf9.py
nf9-1.4.3.dist-info/METADATA
nf9-1.4.3.dist-info/WHEEL
nf9-1.4.3.dist-info/top_level.txt
nf9-1.4.3.dist-info/RECORD
